Thaispoon/Spoonerism.py
Thaispoon/__init__.py
Thaispoon-0.0.2.dist-info/LICENSE
Thaispoon-0.0.2.dist-info/METADATA
Thaispoon-0.0.2.dist-info/WHEEL
Thaispoon-0.0.2.dist-info/top_level.txt
Thaispoon-0.0.2.dist-info/RECORD
