Metadata-Version: 2.1
Name: Thaispoon
Version: 0.0.2
Summary: A small package for thai Spoonerism
Home-page: https://github.com/saalimon/Loolang
Author: Deduq
Author-email: niti08@gmail.com
License: UNKNOWN
Platform: UNKNOWN
Classifier: Programming Language :: Python :: 3
Classifier: License :: OSI Approved :: MIT License
Classifier: Operating System :: OS Independent
Requires-Python: >=3.6
Requires-Dist: pythainlp (==2.1.4)
